seismic_canvas/__init__.py
seismic_canvas/axis_aligned_image.py
seismic_canvas/colorbar.py
seismic_canvas/colorbar_MPL.py
seismic_canvas/seismic_canvas.py
seismic_canvas/volume_slices.py
seismic_canvas/xyz_axis.py
seismic_canvas-0.1.0.dist-info/LICENSE
seismic_canvas-0.1.0.dist-info/METADATA
seismic_canvas-0.1.0.dist-info/WHEEL
seismic_canvas-0.1.0.dist-info/top_level.txt
seismic_canvas-0.1.0.dist-info/zip-safe
seismic_canvas-0.1.0.dist-info/RECORD
