Metadata-Version: 2.1
Name: seismic-canvas
Version: 0.1.0
Summary: An interactive 3D visualization tool mainly designed for seismic data
Home-page: https://github.com/yunzhishi/seismic-canvas
Author: Yunzhi Shi
Author-email: yunzhi.shi.phd@gmail.com
License: MIT
Platform: UNKNOWN
Classifier: Development Status :: 4 - Beta
Classifier: License :: OSI Approved :: MIT License
Classifier: Intended Audience :: Science/Research
Classifier: Operating System :: OS Independent
Classifier: Programming Language :: Python
Classifier: Programming Language :: Python :: 3
Classifier: Programming Language :: Python :: 3.6
Classifier: Programming Language :: Python :: 3.7
Classifier: Programming Language :: Python :: 3.8
Requires-Dist: numpy
Requires-Dist: vispy
Requires-Dist: PyQt5
Requires-Dist: PyOpenGL
Requires-Dist: matplotlib
